ml_inspector/__init__.py
ml_inspector/_metrics_curves.py
ml_inspector/calibration_curves.py
ml_inspector/confusion_matrix.py
ml_inspector/feature_importance.py
ml_inspector/gain_curves.py
ml_inspector/learning_curves.py
ml_inspector/partial_dependence.py
ml_inspector/precision_recall_curves.py
ml_inspector/predictions.py
ml_inspector/predictions_regression.py
ml_inspector/roc_curves.py
ml_inspector/shapley.py
ml_inspector/utils.py
ml_inspector/feature_distribution/__init__.py
ml_inspector/feature_distribution/classification.py
ml_inspector/feature_distribution/regression.py
ml_inspector-0.3.3.dist-info/licenses/LICENSE
ml_inspector-0.3.3.dist-info/METADATA
ml_inspector-0.3.3.dist-info/WHEEL
ml_inspector-0.3.3.dist-info/top_level.txt
ml_inspector-0.3.3.dist-info/RECORD
