Metadata-Version: 2.4
Name: ml-inspector
Version: 0.3.3
Summary: User friendly tools to understand machine learning models
Author-email: Olivier Bougeant <olivierbougeant@gmail.com>
Project-URL: Homepage, https://github.com/Bougeant/ml-inspector
Classifier: Programming Language :: Python :: 3
Classifier: License :: OSI Approved :: Apache Software License
Classifier: Operating System :: OS Independent
Requires-Python: >=3.8
License-File: LICENSE
Requires-Dist: pandas
Requires-Dist: scikit-learn
Requires-Dist: plotly
Requires-Dist: seaborn
Requires-Dist: tqdm
Requires-Dist: statsmodels
Requires-Dist: shap
Provides-Extra: dev
Requires-Dist: pytest; extra == "dev"
Requires-Dist: black; extra == "dev"
Requires-Dist: isort; extra == "dev"
Requires-Dist: flake8; extra == "dev"
Requires-Dist: pytest-cov; extra == "dev"
Dynamic: license-file
